tilequant_dsoinfo.py
libtilequant.so
tilequant/py.typed
tilequant/image_converter.py
tilequant/__init__.py
tilequant/transparency_handler.py
tilequant/util.py
tilequant/cli.py
tilequant/legacy/run.py
tilequant/legacy/palette_merger.py
tilequant/legacy/image_converter.py
tilequant/legacy/__init__.py
tilequant-1.2.0.dist-info/METADATA
tilequant-1.2.0.dist-info/RECORD
tilequant-1.2.0.dist-info/top_level.txt
tilequant-1.2.0.dist-info/WHEEL
tilequant-1.2.0.dist-info/LICENSE
tilequant-1.2.0.dist-info/entry_points.txt
