Metadata-Version: 2.1
Name: tilequant
Version: 1.2.0
Summary: Tool for quantizing image colors using tile-based palette restrictions
Author-email: "Marco \"Capypara\" Köpcke" <hello@capypara.de>
Project-URL: Source, https://github.com/SkyTemple/tilequant/
Classifier: Development Status :: 4 - Beta
Classifier: Programming Language :: Python
Classifier: License :: OSI Approved :: GNU General Public License v3 or later (GPLv3+)
Classifier: Topic :: Multimedia :: Graphics
Classifier: Programming Language :: Python :: 3.10
Classifier: Programming Language :: Python :: 3.11
Classifier: Programming Language :: Python :: 3.12
Classifier: Programming Language :: Python :: 3.13
Requires-Python: >=3.10
License-File: LICENSE
Requires-Dist: Pillow>=10.0.0
Requires-Dist: ordered-set~=4.1.0
Requires-Dist: sortedcollections~=2.1.0
Requires-Dist: click~=8.1.3
Requires-Dist: setuptools_dso~=2.9
